src/__init__.py
src/main.py
src/manage_examples.py
docurl-0.6.2.dist-info/METADATA
docurl-0.6.2.dist-info/WHEEL
docurl-0.6.2.dist-info/entry_points.txt
docurl-0.6.2.dist-info/top_level.txt
docurl-0.6.2.dist-info/RECORD
