Metadata-Version: 2.1
Name: docurl
Version: 0.6.2
Summary: UNKNOWN
Home-page: https://github.com/mongodb/docs-docurl
License: UNKNOWN
Platform: UNKNOWN
Requires-Dist: Click
Requires-Dist: tomli
Requires-Dist: tomli-w
Requires-Dist: PyGithub
Requires-Dist: tomlkit
Requires-Dist: termcolor
